plex_letterboxd/__init__.py
plex_letterboxd/cli.py
plex_letterboxd/client.py
plex_letterboxd/config.py
plex_letterboxd/csv.py
plex_letterboxd-0.5.dist-info/METADATA
plex_letterboxd-0.5.dist-info/WHEEL
plex_letterboxd-0.5.dist-info/entry_points.txt
plex_letterboxd-0.5.dist-info/licenses/LICENSE
plex_letterboxd-0.5.dist-info/RECORD
