Metadata-Version: 2.4
Name: plex-letterboxd
Version: 0.5
Summary: Export Plex watch history to Letterboxd-compatible CSV format
Project-URL: Repository, https://github.com/brege/plex-letterboxd
Author: Wyatt Brege
License-Expression: MIT
License-File: LICENSE
Classifier: Development Status :: 4 - Beta
Classifier: Environment :: Console
Classifier: License :: OSI Approved :: MIT License
Classifier: Programming Language :: Python :: 3
Classifier: Topic :: Multimedia
Requires-Python: >=3.9
Requires-Dist: click>=8.1.7
Requires-Dist: plexapi>=4.17.1
Requires-Dist: pyyaml>=6.0.2
